djlds/__about__.py
djlds/__init__.py
djlds/admin.py
djlds/import_export.py
djlds/model.py
djlds/timezone.py
djlds/user.py
djlds/util.py
djlds/xlsx_util.py
djlds/management/__init__.py
djlds/management/commands/__init__.py
djlds-2024.1.15.dist-info/LICENSE
djlds-2024.1.15.dist-info/METADATA
djlds-2024.1.15.dist-info/WHEEL
djlds-2024.1.15.dist-info/top_level.txt
djlds-2024.1.15.dist-info/RECORD
