Metadata-Version: 2.1
Name: djlds
Version: 2024.1.15
Summary: 常用 Django 功能集合，为了多平台，多电脑调用方便!
Home-page: https://github.com/ldsxp/django-utils-lds
Download-URL: https://pypi.org/project/django-utils-lds
Author: lds
Author-email: 85176878@qq.com
License: GNU GPL 3
Keywords: django,utils
Platform: any
Classifier: Development Status :: 5 - Production/Stable
Classifier: Environment :: Web Environment
Classifier: Framework :: Django
Classifier: Framework :: Django :: 2.2
Classifier: Intended Audience :: Developers
Classifier: License :: OSI Approved :: GNU General Public License (GPL)
Classifier: Operating System :: OS Independent
Classifier: Programming Language :: Python
Classifier: Programming Language :: Python :: 3.6
Requires-Python: >=3.6
License-File: LICENSE
Requires-Dist: ilds
Requires-Dist: colorama
Requires-Dist: django-admin-generator >=2.6.0
Requires-Dist: Django >=2.2
Provides-Extra: dev
Requires-Dist: wheel ; extra == 'dev'
Requires-Dist: twine ; extra == 'dev'
